{
  "iteration": 5,
  "candidate_a": "candidate_v4 (current best)",
  "candidate_b": "candidate_v5",
  "changelog_b": "Restored Escape.tech sourcing context ('scanned apps in production'). Changed 2nd 'semantic analysis' to 'deep code analysis' to reduce repetition. Added 'on GitHub' to opening consequence for specificity. Minimal changes — approaching convergence.",
  "dimension_results": [
    {
      "dimension": "Audience Fit (0.18)",
      "winner": "Tie",
      "score_a": 5,
      "score_b": 5,
      "confidence": 0.55,
      "reason": "Both are ceiling-level for this audience. No meaningful difference.",
      "evidence_a": ["Tightly targeted throughout"],
      "evidence_b": ["Same targeting, 'on GitHub' adds marginal specificity"]
    },
    {
      "dimension": "Clarity (0.14)",
      "winner": "Tie",
      "score_a": 4,
      "score_b": 4,
      "confidence": 0.55,
      "reason": "Both are clear. No meaningful difference.",
      "evidence_a": ["Clear"],
      "evidence_b": ["Clear"]
    },
    {
      "dimension": "Structure/Flow (0.12)",
      "winner": "Tie",
      "score_a": 5,
      "score_b": 5,
      "confidence": 0.55,
      "reason": "Identical structure.",
      "evidence_a": ["Strong arc"],
      "evidence_b": ["Same arc"]
    },
    {
      "dimension": "Novelty/Insight (0.12)",
      "winner": "Tie",
      "score_a": 5,
      "score_b": 5,
      "confidence": 0.55,
      "reason": "Same insights in both.",
      "evidence_a": ["Human mistakes vs AI mistakes framing"],
      "evidence_b": ["Same"]
    },
    {
      "dimension": "Factual Caution (0.10)",
      "winner": "B",
      "score_a": 4,
      "score_b": 4,
      "confidence": 0.60,
      "reason": "B restores the Escape.tech methodology context and adds 'on GitHub' to the opening scenario, making it more specific and grounded.",
      "evidence_a": ["Removed Escape.tech context in v4"],
      "evidence_b": ["\"(Escape.tech scanned apps in production)\" — restored sourcing context", "\"someone found the key on GitHub\" — specific and plausible"]
    },
    {
      "dimension": "Persuasiveness (0.10)",
      "winner": "Tie",
      "score_a": 5,
      "score_b": 5,
      "confidence": 0.55,
      "reason": "Both highly persuasive. Marginal difference only.",
      "evidence_a": ["Strong"],
      "evidence_b": ["Same"]
    },
    {
      "dimension": "CTA Strength (0.12)",
      "winner": "Tie",
      "score_a": 5,
      "score_b": 5,
      "confidence": 0.55,
      "reason": "CTA unchanged from v3.",
      "evidence_a": ["Excellent CTA flow"],
      "evidence_b": ["Same"]
    },
    {
      "dimension": "Brand-Tone Consistency (0.12)",
      "winner": "B",
      "score_a": 5,
      "score_b": 5,
      "confidence": 0.55,
      "reason": "B resolves the 'semantic analysis' repetition issue — using 'deep code analysis' in one place reads slightly better.",
      "evidence_a": ["\"semantic analysis\" appears twice"],
      "evidence_b": ["Varied: 'deep code analysis' in injection section, 'semantic analysis' in auth section"]
    }
  ],
  "overall_winner": "B",
  "weighted_score_a": 48.0,
  "weighted_score_b": 48.2,
  "key_improvements_for_next_iteration": [
    "CONVERGED — further iterations will yield diminishing returns",
    "The blog is strong across all dimensions. Main remaining opportunity is real-world testing with actual readers.",
    "Could consider adding a downloadable checklist or one-pager as a lead magnet tied to the CTA",
    "The Escape.tech data could be updated when newer studies become available"
  ],
  "judge_flags": ["possible_reward_hacking — v4→v5 changes are trivial; blog has converged"]
}
